{".class": "MypyFile", "_fullname": "list_Collections", "is_partial_stub_package": false, "is_stub": false, "names": {".class": "SymbolTable", "__doc__": {".class": "SymbolTableNode", "kind": "Gdef", "node": {".class": "Var", "flags": ["is_ready"], "fullname": "list_Collections.__doc__", "name": "__doc__", "type": "builtins.str"}}, "__file__": {".class": "SymbolTableNode", "kind": "Gdef", "node": {".class": "Var", "flags": ["is_ready"], "fullname": "list_Collections.__file__", "name": "__file__", "type": "builtins.str"}}, "__name__": {".class": "SymbolTableNode", "kind": "Gdef", "node": {".class": "Var", "flags": ["is_ready"], "fullname": "list_Collections.__name__", "name": "__name__", "type": "builtins.str"}}, "__package__": {".class": "SymbolTableNode", "kind": "Gdef", "node": {".class": "Var", "flags": ["is_ready"], "fullname": "list_Collections.__package__", "name": "__package__", "type": "builtins.str"}}, "array": {".class": "SymbolTableNode", "cross_ref": "array.array", "kind": "Gdef"}, "names": {".class": "SymbolTableNode", "kind": "Gdef", "node": {".class": "Var", "flags": [], "fullname": "list_Collections.names", "name": "names", "type": {".class": "Instance", "args": ["builtins.str"], "type_ref": "builtins.list"}}}, "scores": {".class": "SymbolTableNode", "kind": "Gdef", "node": {".class": "Var", "flags": [], "fullname": "list_Collections.scores", "name": "scores", "type": {".class": "Instance", "args": ["builtins.int"], "type_ref": "builtins.list"}}}}, "path": "c:\\Users\\Lloyd Harris\\Documents\\Training 2020\\Python\\list_Collections.py"}